{"cameraMode":{"drawMode":0,"name":"Shaded","section":"Shading Mode"},"sceneLighting":true,"audioPlay":false,"sceneViewState":{"m_AlwaysRefresh":false,"showFog":true,"showSkybox":true,"showFlares":true,"showImageEffects":true,"showParticleSystems":true,"showVisualEffectGraphs":true,"m_FxEnabled":true},"in2DMode":false,"pivot":{"x":-12.382234573364258,"y":-5.146172046661377,"z":8.681191444396973},"rotation":{"x":0.0991092175245285,"y":-0.8754894733428955,"z":0.20314368605613709,"w":0.42712637782096865},"size":1.9746688604354859,"orthographic":false}